hallux/VERSION
hallux/__init__.py
hallux/auxilary.py
hallux/logger.py
hallux/main.py
hallux/models.py
hallux/backends/dummy_backend.py
hallux/backends/factory.py
hallux/backends/litellm.py
hallux/backends/openai_backend.py
hallux/backends/query_backend.py
hallux/backends/rest_backend.py
hallux/issues/annotations.py
hallux/issues/issue.py
hallux/proposals/diff_proposal.py
hallux/proposals/proposal_engine.py
hallux/proposals/python_proposal.py
hallux/proposals/simple_proposal.py
hallux/targets/diff.py
hallux/targets/filesystem.py
hallux/targets/git_commit.py
hallux/targets/github_suggestion.py
hallux/targets/gitlab_suggestion.py
hallux/tools/factory.py
hallux/tools/issue_solver.py
hallux/tools/cpp/cpp.py
hallux/tools/cpp/issue.py
hallux/tools/cpp/make_target_solver.py
hallux/tools/mypy/solver.py
hallux/tools/python/python_issue.py
hallux/tools/ruff/solver.py
hallux/tools/sonarqube/issue.py
hallux/tools/sonarqube/solver.py
hallux-0.2.71.dist-info/LICENSE.txt
hallux-0.2.71.dist-info/METADATA
hallux-0.2.71.dist-info/WHEEL
hallux-0.2.71.dist-info/entry_points.txt
hallux-0.2.71.dist-info/top_level.txt
hallux-0.2.71.dist-info/RECORD
