Metadata-Version: 2.2
Name: hallux
Version: 0.2.71
Summary: Hallux - Convenient AI Code Quality Assistant
Author-email: Hallux Team <team@hallux.dev>
License:                     GNU GENERAL PUBLIC LICENSE
Project-URL: Homepage, https://github.com/halluxdev/hallux
Project-URL: Bug Tracker, https://github.com/halluxdev/hallux/issues
Classifier: Development Status :: 4 - Beta
Classifier: Programming Language :: Python :: 3.8
Classifier: Programming Language :: Python :: 3.9
Classifier: Programming Language :: Python :: 3.10
Classifier: Programming Language :: Python :: 3.11
Classifier: License :: OSI Approved :: GNU General Public License v3 (GPLv3)
Classifier: Topic :: Scientific/Engineering :: Artificial Intelligence
Requires-Python: <4.0,>=3.8
License-File: LICENSE.txt
Requires-Dist: PyGithub==2.1.1
Requires-Dist: colorlog==6.7.0
Requires-Dist: requests==2.32.0
Requires-Dist: unidiff==0.7.5
Requires-Dist: litellm==1.48.7
Provides-Extra: test
Requires-Dist: mypy==1.4.1; extra == "test"
Requires-Dist: black==24.3.0; extra == "test"
Requires-Dist: ruff==0.0.272; extra == "test"
Requires-Dist: pytest==8.3.3; extra == "test"
Requires-Dist: pytest-cov==5.0.0; extra == "test"
Requires-Dist: isort==5.12.0; extra == "test"
Requires-Dist: wheel==0.40.0; extra == "test"
Requires-Dist: pyinstaller>=5.13.1; extra == "test"
